[
    {
        "nombre": "Julian David",
        "apellido": "Pedrozo Rangel",
        "identificacion": "1044623839",
        "edad": 17,
        "telefono": "3028456767",
        "correo": "julianpedrozzo10@gmail.com",
        "contrasena":"julian123",
        "rol":"Administrador"
    },
    {
        "nombre": "Julian David",
        "apellido": "Pedrozo Rangel",
        "identificacion": "1234567890",
        "edad": 17,
        "telefono": "3028456767",
        "correo": "julianpedrozzo10@gmail.com",
        "contrasena":"12345",
        "rol":"Coordinador",
        "institucion":"colegio 1"
    },
    {
        "nombre": "Raul Felipe",
        "apellido": "Rodriguez gil",
        "identificacion": "0123456789",
        "edad": 45,
        "telefono": "3010101010",
        "correo": "rr@gmail.com",
        "contrasena":"0000",
        "rol":"Docente",
        "institucion":"Colegio 1",
        "materia":"Matematicas"
    },
    {
        "nombre": "Ian Andres",
        "apellido": "Campo Bosque",
        "identificacion": "9876543210",
        "edad": 15,
        "telefono": "3003003030",
        "correo": "ianthebest@gmail.com",
        "contrasena":"123",
        "rol":"Estudiante",
        "institucion":"Colegio 1",
        "grado": 11
    }

]
